nxtheme_creator/__init__.py
nxtheme_creator/__main__.py
nxtheme_creator/backends/__init__.py
nxtheme_creator/backends/nxtheme.py
nxtheme_creator/backends/sarc_tool.py
nxtheme_creator/conf.json
nxtheme_creator/img_info.py
nxtheme_creator/layouts/CarefulLayout.jpg
nxtheme_creator/layouts/CarefulLayout.json
nxtheme_creator/layouts/CommonNoFooter.json
nxtheme_creator/layouts/DiamondLayoutHomescreen.jpg
nxtheme_creator/layouts/DiamondLayoutHomescreen.json
nxtheme_creator/layouts/DogeFl.jpg
nxtheme_creator/layouts/DogeFl.json
nxtheme_creator/layouts/DogeLayoutRounded.jpg
nxtheme_creator/layouts/DogeLayoutRounded.json
nxtheme_creator/layouts/FlaunchRounded.jpg
nxtheme_creator/layouts/FlaunchRounded.json
nxtheme_creator/layouts/Flow Layout.jpg
nxtheme_creator/layouts/Flow Layout.json
nxtheme_creator/layouts/GleLk.jpg
nxtheme_creator/layouts/GleLk.json
nxtheme_creator/layouts/JAG Layout.jpg
nxtheme_creator/layouts/JAG Layout.json
nxtheme_creator/layouts/RedAppletButtons.json
nxtheme_creator/layouts/RoundedSmallCompact.jpg
nxtheme_creator/layouts/RoundedSmallCompact.json
nxtheme_creator/layouts/Side Lock.jpg
nxtheme_creator/layouts/Side Lock.json
nxtheme_creator/layouts/SimpleLockscreenLayout.jpg
nxtheme_creator/layouts/SimpleLockscreenLayout.json
nxtheme_creator/layouts/SmallCompactHomescreen.jpg
nxtheme_creator/layouts/SmallCompactHomescreen.json
nxtheme_creator/layouts/SuchHm.jpg
nxtheme_creator/layouts/SuchHm.json
nxtheme_creator/layouts/SuchLk.jpg
nxtheme_creator/layouts/SuchLk.json
nxtheme_creator/layouts/Transparant Playerselect 90% Scale centered.jpg
nxtheme_creator/layouts/Transparant Playerselect 90% Scale centered.json
nxtheme_creator/layouts/Transparant Playerselect 90% Scale top.jpg
nxtheme_creator/layouts/Transparant Playerselect 90% Scale top.json
nxtheme_creator/layouts/Transparant Playerselect 90% Scale.jpg
nxtheme_creator/layouts/Transparant Playerselect 90% Scale.json
nxtheme_creator/layouts/Transparant Playerselect centered.jpg
nxtheme_creator-2024.2.dist-info/entry_points.txt
nxtheme_creator-2024.2.dist-info/LICENSE.md
nxtheme_creator-2024.2.dist-info/METADATA
nxtheme_creator-2024.2.dist-info/WHEEL
nxtheme_creator-2024.2.dist-info/RECORD
