Metadata-Version: 2.1
Name: nxtheme_creator
Version: 2024.2
Summary: Tool for making custom Nintendo Switch themes using `SwitchThemes.exe` with images, and a simple config
Home-page: https://github.com/FHPythonUtils/nxtheme-creator
License: GPL-2.0-or-later
Author: FredHappyface
Requires-Python: >=3.8,<4
Classifier: Development Status :: 4 - Beta
Classifier: Intended Audience :: Developers
Classifier: Intended Audience :: Education
Classifier: License :: OSI Approved :: GNU General Public License v2 or later (GPLv2+)
Classifier: Natural Language :: English
Classifier: Operating System :: Microsoft :: Windows
Classifier: Programming Language :: Python :: 3
Classifier: Programming Language :: Python :: 3.8
Classifier: Programming Language :: Python :: 3.9
Classifier: Programming Language :: Python :: 3.10
Classifier: Programming Language :: Python :: 3.11
Classifier: Programming Language :: Python :: 3.12
Classifier: Programming Language :: Python :: Implementation :: CPython
Classifier: Topic :: Software Development :: Libraries :: Python Modules
Classifier: Topic :: Utilities
Requires-Dist: oead (>=1.2.9.post4,<2)
Requires-Dist: pillow (>=10.4.0,<11)
Requires-Dist: sarc (>=2.0.5,<3)
Project-URL: Documentation, https://github.com/FHPythonUtils/nxtheme-creator/blob/master/README.md
Project-URL: Repository, https://github.com/FHPythonUtils/nxtheme-creator
